[
{
    "id":1,
    "title":"Web Development",
    "image":"../images/img1.jpg",
    "description":"Hello this is webd  and you can hire me for your projects"

},
{
    "id":2,
    "title":"Web Development",
    "image":"../images/img1.jpg",
    "description":"Hello this is webd  and you can hire me for your projects"

},
{
    "id":3,
    "title":"Web Development",
    "image":"../images/img1.jpg",
    "description":"Hello this is webd  and you can hire me for your projects"

},
{
    "id":4,
    "title":"Web Development",
    "image":"../images/img1.jpg",
    "description":"Hello this is webd  and you can hire me for your projects"

},
{
    "id":5,
    "title":"Web Development",
    "image":"../images/img1.jpg",
    "description":"Hello this is webd  and you can hire me for your projects"

},
{
    "id":6,
    "title":"Web Development",
    "image":"../images/img1.jpg",
    "description":"Hello this is webd  and you can hire me for your projects"

},
{
    "id":7,
    "title":"Web Development",
    "image":"../images/img1.jpg",
    "description":"Hello this is webd  and you can hire me for your projects"

},
{
    "id":8,
    "title":"Web Development",
    "image":"../images/img1.jpg",
    "description":"Hello this is webd  and you can hire me for your projects"

},
{
    "id":9,
    "title":"Web Development",
    "image":"../images/img1.jpg",
    "description":"Hello this is webd  and you can hire me for your projects"

}








]